__init__.py
whatis.py
whatis-0.0.1.dist-info/LICENSE
whatis-0.0.1.dist-info/METADATA
whatis-0.0.1.dist-info/WHEEL
whatis-0.0.1.dist-info/top_level.txt
whatis-0.0.1.dist-info/RECORD
