Metadata-Version: 2.1
Name: whatis
Version: 0.0.1
Summary: A small Python utility to tell you what an object is
Author-email: Zak Buzzard <zakbuzzard1@gmail.com>
Project-URL: Homepage, https://github.com/zzbuzzard/whatis
Project-URL: Issues, https://github.com/zzbuzzard/whatis/issues
Classifier: Programming Language :: Python :: 3
Classifier: License :: OSI Approved :: MIT License
Classifier: Operating System :: OS Independent
Requires-Python: >=3.5
License-File: LICENSE
